emzed/__init__.py
emzed/__main__.py
emzed/check_pyopenms.py
emzed/db.py
emzed/ext.py
emzed/gui.py
emzed/io.py
emzed/align/__init__.py
emzed/align/mz_align.py
emzed/align/mz_align_routines.py
emzed/align/rt_align.py
emzed/align/sample_alignment.py
emzed/annotate/__init__.py
emzed/annotate/annotate_adducts.py
emzed/chemistry/Elements.xml
emzed/chemistry/__init__.py
emzed/chemistry/abundance.py
emzed/chemistry/adducts.py
emzed/chemistry/elements.py
emzed/chemistry/elements_pubchem.json
emzed/chemistry/fetch_elements_pubchem.py
emzed/chemistry/fit_formula.py
emzed/chemistry/formula_parser.py
emzed/chemistry/isotope_generator.py
emzed/chemistry/mass.py
emzed/chemistry/molecular_formula.py
emzed/chemistry/pubchem.py
emzed/config/__init__.py
emzed/config/config.py
emzed/core/__init__.py
emzed/core/db_backed_dictionary.py
emzed/core/db_backed_model.py
emzed/core/exceptions.py
emzed/core/hashes.py
emzed/core/multiprocessing.py
emzed/ms2/__init__.py
emzed/ms2/attach_ms2_spectra.py
emzed/ms2/merge_spectra.py
emzed/ms2/sirius_export.py
emzed/ms_data/__init__.py
emzed/ms_data/peak_map.py
emzed/ms_data/peak_map_hasher.py
emzed/optimized/__init__.py
emzed/optimized/formula_fit.c
emzed/optimized/formula_fit.cp311-win_amd64.pyd
emzed/optimized/formula_fit.pyx
emzed/peak_picking/__init__.py
emzed/peak_picking/centwave.txt
emzed/peak_picking/extract_chromatograms.py
emzed/peak_picking/extract_ms_chromatograms.py
emzed/peak_picking/run_feature_finder_centwave.py
emzed/peak_picking/run_feature_finder_metabo.py
emzed/peak_picking/run_feature_finder_metabo_on_folder.py
emzed/pyopenms/__init__.py
emzed/pyopenms/optimizations.py
emzed/pyopenms/stderr_redirector.py
emzed/quantification/__init__.py
emzed/quantification/chromatogram_integration.py
emzed/quantification/peak_integration.py
emzed/quantification/utils.py
emzed/quantification/peak_shape_models/__init__.py
emzed/quantification/peak_shape_models/asymmetric_gauss_model.py
emzed/quantification/peak_shape_models/base.py
emzed-3.0.0a24.dist-info/licenses/LICENSE
emzed-3.0.0a24.dist-info/METADATA
emzed-3.0.0a24.dist-info/WHEEL
emzed-3.0.0a24.dist-info/top_level.txt
emzed-3.0.0a24.dist-info/RECORD
