Metadata-Version: 2.4
Name: emzed
Version: 3.0.0a24
Author-email: Uwe Schmitt <uwe.schmitt@id.ethz.ch>
License: MIT
Project-URL: Homepage, https://emzed.ethz.ch/3/emzed
Requires-Python: <3.13,>=3.10
License-File: LICENSE
Requires-Dist: IsoSpecPy==2.2.2
Requires-Dist: pandas>=2.0.1
Requires-Dist: pyper==1.1.1
Requires-Dist: pywin32>=0.3; platform_system == "Windows"
Requires-Dist: dill>=0.3.9
Requires-Dist: jinja2>=3.1.4
Requires-Dist: numpy
Requires-Dist: openpyxl>=3.1.5
Requires-Dist: matplotlib>=3.9.2
Requires-Dist: requests>=2.32.3
Requires-Dist: scikit-learn>=1.5.2
Requires-Dist: tqdm>=4.66.6
Requires-Dist: python-calamine>=0.2.3
Dynamic: license-file
